setup.py
distributions_formulae/Binomialdistribution.py
distributions_formulae/Gaussiandistribution.py
distributions_formulae/Generaldistribution.py
distributions_formulae/__init__.py
distributions_formulae.egg-info/PKG-INFO
distributions_formulae.egg-info/SOURCES.txt
distributions_formulae.egg-info/dependency_links.txt
distributions_formulae.egg-info/not-zip-safe
distributions_formulae.egg-info/top_level.txt