Metadata-Version: 1.0
Name: distributions-formulae
Version: 0.1
Summary: Gaussian and Binomial distributions formulae
Home-page: UNKNOWN
Author: Digant Garude
Author-email: digant.dg07@gmail.com
License: UNKNOWN
Platform: UNKNOWN
